{
  "accounts": {
    "production02": {
      "account_id": "515688267891",
      "admin_allow_list": [],
      "force_destroy_bucket": false,
      "front_allow_list": [
        "0.0.0.0/0"
      ],
      "ga_default": "UA-57312200-3",
      "ga_gds": "UA-145652997-1",
      "subdomain_enabled": false,
      "is_production": 1,
      "secrets_prefix": "production02",
      "task_count": 3,
      "scan_count": 2,
      "symfony_env": "prod",
      "db_subnet_group": "rds-private-subnets-prod-vpc",
      "ec_subnet_group": "ec-pvt-subnets-prod-vpc",
      "sirius_api_account": "649098267436",
      "state_source": "production",
      "elasticache_count": 2,
      "always_on": true,
      "cpu_low": "512",
      "cpu_medium": "1024",
      "cpu_high": "2048",
      "memory_low": "1024",
      "memory_medium": "2048",
      "memory_high": "4096",
      "backup_retention_period": 14,
      "psql_engine_version": "9.6.16",
      "alarms_active": true,
      "dr_backup": true
    },
    "preproduction": {
      "account_id": "454262938596",
      "admin_allow_list": [],
      "force_destroy_bucket": false,
      "front_allow_list": [],
      "ga_default": "UA-57312200-3",
      "ga_gds": "NotApplicable",
      "subdomain_enabled": true,
      "is_production": 0,
      "secrets_prefix": "",
      "task_count": 2,
      "scan_count": 1,
      "symfony_env": "prod",
      "db_subnet_group": "private",
      "ec_subnet_group": "private",
      "sirius_api_account": "492687888235",
      "state_source": "preproduction",
      "elasticache_count": 2,
      "always_on": true,
      "cpu_low": "512",
      "cpu_medium": "1024",
      "cpu_high": "2048",
      "memory_low": "1024",
      "memory_medium": "2048",
      "memory_high": "4096",
      "backup_retention_period": 1,
      "psql_engine_version": "10.13",
      "alarms_active": false,
      "dr_backup": false
    },
    "training": {
      "account_id": "515688267891",
      "admin_allow_list": [],
      "force_destroy_bucket": true,
      "front_allow_list": [],
      "ga_default": "UA-57312200-2",
      "ga_gds": "NotApplicable",
      "subdomain_enabled": true,
      "is_production": 0,
      "secrets_prefix": "training",
      "task_count": 1,
      "scan_count": 1,
      "symfony_env": "prod",
      "db_subnet_group": "rds-private-subnets-prod-vpc",
      "ec_subnet_group": "ec-pvt-subnets-prod-vpc",
      "sirius_api_account": "649098267436",
      "state_source": "production",
      "elasticache_count": 1,
      "always_on": true,
      "cpu_low": "512",
      "cpu_medium": "1024",
      "cpu_high": "2048",
      "memory_low": "1024",
      "memory_medium": "2048",
      "memory_high": "4096",
      "backup_retention_period": 1,
      "psql_engine_version": "10.13",
      "alarms_active": true,
      "dr_backup": false
    },
    "integration": {
      "account_id": "454262938596",
      "admin_allow_list": [],
      "force_destroy_bucket": true,
      "front_allow_list": [],
      "ga_default": "UA-57312200-2",
      "ga_gds": "NotApplicable",
      "subdomain_enabled": true,
      "is_production": 0,
      "secrets_prefix": "",
      "task_count": 2,
      "scan_count": 1,
      "symfony_env": "test",
      "db_subnet_group": "private",
      "ec_subnet_group": "private",
      "sirius_api_account": "492687888235",
      "state_source": "preproduction",
      "elasticache_count": 1,
      "always_on": true,
      "cpu_low": "256",
      "cpu_medium": "512",
      "cpu_high": "1024",
      "memory_low": "512",
      "memory_medium": "1024",
      "memory_high": "2048",
      "backup_retention_period": 1,
      "psql_engine_version": "10.13",
      "alarms_active": true,
      "dr_backup": true
    },
    "development": {
      "account_id": "248804316466",
      "admin_allow_list": [],
      "send_internal_email": false,
      "force_destroy_bucket": true,
      "front_allow_list": [
        "0.0.0.0/0"
      ],
      "ga_default": "UA-57312200-2",
      "ga_gds": "NotApplicable",
      "subdomain_enabled": true,
      "is_production": 0,
      "secrets_prefix": "default",
      "task_count": 1,
      "scan_count": 1,
      "symfony_env": "test",
      "db_subnet_group": "private",
      "ec_subnet_group": "private",
      "sirius_api_account": "248804316466",
      "state_source": "development",
      "elasticache_count": 1,
      "always_on": false,
      "cpu_low": "256",
      "cpu_medium": "512",
      "cpu_high": "1024",
      "memory_low": "512",
      "memory_medium": "1024",
      "memory_high": "2048",
      "backup_retention_period": 1,
      "psql_engine_version": "10.7",
      "alarms_active": false,
      "dr_backup": false
    },
    "default": {
      "account_id": "248804316466",
      "admin_allow_list": [],
      "send_internal_email": false,
      "force_destroy_bucket": true,
      "front_allow_list": [],
      "ga_default": "UA-57312200-2",
      "ga_gds": "NotApplicable",
      "subdomain_enabled": true,
      "is_production": 0,
      "secrets_prefix": "default",
      "task_count": 1,
      "scan_count": 1,
      "symfony_env": "test",
      "db_subnet_group": "private",
      "ec_subnet_group": "private",
      "sirius_api_account": "288342028542",
      "state_source": "development",
      "elasticache_count": 1,
      "always_on": false,
      "cpu_low": "256",
      "cpu_medium": "512",
      "cpu_high": "1024",
      "memory_low": "512",
      "memory_medium": "1024",
      "memory_high": "2048",
      "backup_retention_period": 1,
      "psql_engine_version": "10.7",
      "alarms_active": false,
      "dr_backup": false
    }
  }
}
